ql_sdk
