Metadata-Version: 2.1
Name: ql-sdk
Version: 0.0.4
Summary: 青龙面板API封装
Home-page: UNKNOWN
Author: tushen
Author-email: 2256485749@qq.com
License: MIT Licence
Keywords: ql,青龙,tushen
Platform: any
